Simulation/ff_latch/dff_sync_rst/dff_async_rst.v
module dff 	( input d,
              input rstn,
              input clk,
              output reg q);

	always @ (posedge clk)
       if (!rstn)
          q <= 0;
       else
          q <= d;
endmodule

Simulation/ff_latch/dff_sync_rst/tb.v
module tb_dff;
	reg clk;
	reg d;
	reg rstn;
	reg [2:0] delay;
	wire q;
    integer i;

    dff  dff0 ( .d(d),
                .rstn (rstn),
                .clk (clk),
                .q (q));

    // Generate clock
    always #10 clk = ~clk;

    initial begin
    $dumpfile("dump.vcd");   // 波形文件名
    $dumpvars(0, tb_dff);    // tb 是你的 testbench module 名
    end

    // Testcase
    initial begin
    	clk <= 0;
    	d <= 0;
    	rstn <= 0;
        
    	#10 d <= 1;
    	#20 rstn <= 1;
        #25 d <= 0;
        #30 d <= 1;
        #35 rstn <= 0;
        #40
        #45
        $finish;
    end
endmodule

Simulation/ff_latch/dff_sync_rst/dump.vcd
$date
	Mon Apr 06 21:33:50 2026
$end
$version
	Icarus Verilog
$end
$timescale
	1s
$end
$scope module tb_dff $end
$var wire 1 ! q $end
$var reg 1 " clk $end
$var reg 1 # d $end
$var reg 1 $ rstn $end
$scope module dff0 $end
$var wire 1 " clk $end
$var wire 1 # d $end
$var wire 1 $ rstn $end
$var reg 1 ! q $end
$upscope $end
$upscope $end
$enddefinitions $end
$comment Show the parameter values. $end
$dumpall
$end
#0
$dumpvars
0$
0#
0"
x!
$end
#10
0!
1#
1"
#20
0"
#30
1$
1"
#40
0"
#50
1!
1"
#55
0#
#60
0"
#70
0!
1"
#80
0"
#85
1#
#90
1!
1"
#100
0"
#110
1"
#120
0$
0"
#130
0!
1"
