Simulation/RegisterVector.v
//Verilog vectors are declared using a size range on the left side of the variable name and these get realized into flops that match
//the size of the variable. In the code shown below, the design module accepts clock, reset and some control signals to read and write
//into the block. It contains a 16-bit storage element called register which simply gets updated during writes and returns the current
//value during reads. The register is written when sel and wr are high on the same clock edge. It returns the current data when sel is
//high and wr is low.

module des (input         clk,
            input         rstn,
            input         wr,
            input         sel,
            input [15:0]  wdata,
            output [15:0] rdata,
			output        flag);

reg iFlag;
reg[15:0] register;
always @ (posedge clk) begin
	iFlag <= ~iFlag;
    if (~rstn) begin
        register <= 0;
		iFlag <= 0;
	end
    else begin
        if (sel & wr) begin
            register <= wdata;
		end
    end
    $display("time=%0t register=%h", $time, register);
end

	assign rdata = (sel & ~wr) ? register : 0;
	assign flag = iFlag;
endmodule

Simulation/tb.v
module tb;

reg clk;
reg rstn;
reg wr;
reg sel;
wire flag;
reg [15:0] wdata;
wire [15:0] rdata;

des dut (
 .clk(clk),
 .rstn(rstn),
 .wr(wr),
 .sel(sel),
 .wdata(wdata),
 .rdata(rdata),
 .flag(flag)
);

initial begin
$dumpfile("RegisterVector.vcd");
$dumpvars(0, tb.dut);
end

// clock generation
initial begin
 clk = 0;
 forever #5 clk = ~clk;
end

// stimulus
initial begin
 rstn = 0;
 wr = 0;
 sel = 0;
 wdata = 0;

 #10 rstn = 1;

 #10 sel = 1;
 wr = 1;
 wdata = 16'h1234;

 #10 wr = 0;

 #20 $finish;
end

endmodule

Simulation/RegisterVector.vcd
$date
	Sat Mar 21 09:09:31 2026
$end
$version
	Icarus Verilog
$end
$timescale
	1s
$end
$scope module tb $end
$scope module dut $end
$var wire 1 ! clk $end
$var wire 1 " flag $end
$var wire 1 # rstn $end
$var wire 1 $ sel $end
$var wire 16 % wdata [15:0] $end
$var wire 1 & wr $end
$var wire 16 ' rdata [15:0] $end
$var reg 1 ( iFlag $end
$var reg 16 ) register [15:0] $end
$upscope $end
$upscope $end
$enddefinitions $end
$comment Show the parameter values. $end
$dumpall
$end
#0
$dumpvars
bx )
x(
b0 '
0&
b0 %
0$
0#
x"
0!
$end
#5
0"
0(
b0 )
1!
#10
0!
1#
#15
1"
1(
1!
#20
0!
b1001000110100 %
1&
1$
#25
b1001000110100 )
0"
0(
1!
#30
b1001000110100 '
0!
0&
#35
1"
1(
1!
#40
0!
#45
0"
0(
1!
