Simulation/ff_latch/d_latch/d_latch.v
module d_latch ( input d,
                 input en,
                 input rstn,
                 output reg q);

    always @ (*) begin
        if (!rstn)
            q <= 0;
        else if (en)
            q <= d;
    end

endmodule

Simulation/ff_latch/d_latch/tb.v
module tb_latch;
   // Declare variables that can be used to drive values to the design
   reg d;
   reg en;
   reg rstn;
   reg [2:0] delay;
   reg [1:0] delay2;
   integer i;

   // Instantiate design and connect design ports with TB signals
   d_latch  dl0 ( .d (d),
                  .en (en),
                  .rstn (rstn),
                  .q (q));

    initial begin
    $dumpfile("dump.vcd");   // 波形文件名
    $dumpvars(0, tb_latch);        // tb 是你的 testbench module 名
    end

   // This initial block forms the stimulus to test the design
   initial begin
      $monitor ("[%0t] en=%0b d=%0b q=%0b", $time, en, d, q);

      // 1. Initialize testbench variables
      d <= 0;
      en <= 0;
      rstn <= 0;

      // 2. Release reset
      #10 rstn <= 1;

      // 3. Randomly change d and enable
      for (i = 0; i < 5; i=i+1) begin
         delay = $random;
         delay2 = $random;
         #(delay2) en <= ~en;
         #(delay) d <= i;
      end
   end
endmodule

Simulation/ff_latch/d_latch/dump.vcd
$date
	Mon Apr 06 05:42:40 2026
$end
$version
	Icarus Verilog
$end
$timescale
	1s
$end
$scope module tb_latch $end
$var wire 1 ! q $end
$var reg 1 " d $end
$var reg 3 # delay [2:0] $end
$var reg 2 $ delay2 [1:0] $end
$var reg 1 % en $end
$var reg 1 & rstn $end
$var integer 32 ' i [31:0] $end
$scope module dl0 $end
$var wire 1 " d $end
$var wire 1 % en $end
$var wire 1 & rstn $end
$var reg 1 ! q $end
$upscope $end
$upscope $end
$enddefinitions $end
$comment Show the parameter values. $end
$dumpall
$end
#0
$dumpvars
bx '
0&
0%
bx $
bx #
0"
0!
$end
#10
1&
b1 $
b100 #
b0 '
#11
1%
#15
b11 $
b1 #
b1 '
#18
0%
#19
1"
b1 $
b101 #
b10 '
#20
1!
1%
#25
0!
0"
b10 $
b11 '
#27
0%
#32
1"
b1 $
b1 #
b100 '
#33
1!
1%
#34
0!
0"
b101 '
