Simulation/ff_latch/tff/tff.v
module tff ( 	input clk,
            	input rstn,
            	input t,
            output reg q);

  always @ (posedge clk) begin
    if (!rstn)
      q <= 0;
    else
    	if (t)
      		q <= ~q;
    	else
      		q <= q;
  end
endmodule

Simulation/ff_latch/tff/tb.v
module tb;

reg clk;
reg rstn;
reg t;
wire q;   // ✅ 补上

tff u0 (
    .clk(clk),
    .rstn(rstn),
    .t(t),
    .q(q)
);

// clock
always #5 clk = ~clk;

// waveform
initial begin
    $dumpfile("dump.vcd");
    $dumpvars(0, tb);
end

// stimulus
initial begin
    clk = 0;
    rstn = 0;
    t = 0;

    $monitor ("T=%0t rstn=%0b t=%0b q=%0b", $time, rstn, t, q);

    #10 rstn = 1;   // ✅ 正确复位释放

    #10 t = 1;
    #20 t = 0;
    #30 t = 1;
    #40 t = 0;

    #20;
    $finish;
end

endmodule

Simulation/ff_latch/tff/dump.vcd
$date
	Mon Apr 06 23:37:21 2026
$end
$version
	Icarus Verilog
$end
$timescale
	1s
$end
$scope module tb $end
$var wire 1 ! q $end
$var reg 1 " clk $end
$var reg 1 # rstn $end
$var reg 1 $ t $end
$scope module u0 $end
$var wire 1 " clk $end
$var wire 1 # rstn $end
$var wire 1 $ t $end
$var reg 1 ! q $end
$upscope $end
$upscope $end
$enddefinitions $end
$comment Show the parameter values. $end
$dumpall
$end
#0
$dumpvars
0$
0#
0"
x!
$end
#5
0!
1"
#10
0"
1#
#15
1"
#20
0"
1$
#25
1!
1"
#30
0"
#35
0!
1"
#40
0"
0$
#45
1"
#50
0"
#55
1"
#60
0"
#65
1"
#70
0"
1$
#75
1!
1"
#80
0"
#85
0!
1"
#90
0"
#95
1!
1"
#100
0"
#105
0!
1"
#110
0"
0$
